hypervector/__init__.py
hypervector/errors.py
hypervector/resources/__init__.py
hypervector/resources/abstract/__init__.py
hypervector/resources/abstract/api_resource.py
hypervector/resources/auxilliary/__init__.py
hypervector/resources/auxilliary/revision.py
hypervector/resources/core/__init__.py
hypervector/resources/core/benchmark.py
hypervector/resources/core/definition.py
hypervector/resources/core/ensemble.py
hypervector/resources/core/project.py
hypervector_wrapper-0.0.15.dist-info/LICENSE.txt
hypervector_wrapper-0.0.15.dist-info/METADATA
hypervector_wrapper-0.0.15.dist-info/WHEEL
hypervector_wrapper-0.0.15.dist-info/top_level.txt
hypervector_wrapper-0.0.15.dist-info/RECORD
