Metadata-Version: 2.1
Name: hypervector-wrapper
Version: 0.0.15
Summary: Python wrapper to use the Hypervector API. Better data tests
Home-page: https://github.com/hypervectorio/hypervector-wrapper
Author: Jason Costello, Hypervector Limited
Author-email: jason@hypervector.io
License: UNKNOWN
Platform: UNKNOWN
Classifier: Programming Language :: Python :: 3
Classifier: Programming Language :: Python :: 3.6
Classifier: Intended Audience :: Developers
Classifier: License :: OSI Approved :: MIT License
Classifier: Operating System :: OS Independent
Classifier: Topic :: Software Development :: Libraries :: Python Modules
Requires-Dist: requests (~=2.25.0)
Requires-Dist: numpy (>=1.19.5)
Provides-Extra: dev
Requires-Dist: pytest (>=3.7) ; extra == 'dev'
Requires-Dist: responses (~=0.12.1) ; extra == 'dev'
Requires-Dist: twine (~=3.4.1) ; extra == 'dev'
Requires-Dist: tox (~=3.23.0) ; extra == 'dev'
